tuyapipc/__init__.py
pytuyapi_ipc-1.0.4.dist-info/METADATA
pytuyapi_ipc-1.0.4.dist-info/WHEEL
pytuyapi_ipc-1.0.4.dist-info/top_level.txt
pytuyapi_ipc-1.0.4.dist-info/RECORD
