Metadata-Version: 2.1
Name: pytuyapi-ipc
Version: 1.0.4
Summary: Wrapper around node tuyapi
Home-page: https://github.com/89jd/pytuyapi-ipc
Author: jd89
Author-email: jd89.dev@gmail.com
License: UNKNOWN
Platform: UNKNOWN
